minotor/__init__.py
minotor/command.py
minotor/constants.py
minotor/run.py
minotor/api/__init__.py
minotor/api/base_route.py
minotor/api/data_handler.py
minotor/api/projection_handler.py
minotor/api/training_data_handler.py
minotor/data_managers/__init__.py
minotor/data_managers/data_types.py
minotor/data_managers/file_manager.py
minotor/data_managers/prediction_data.py
minotor/data_managers/preprocessors.py
minotor/data_managers/data_containers/__init__.py
minotor/data_managers/data_containers/feature_phase_container.py
minotor/data_managers/data_containers/features_data_container.py
minotor/data_managers/data_containers/single_feature_data_container.py
minotor/data_managers/data_containers/values_informations.py
minotor/decorators/__init__.py
minotor/decorators/feature_monitoring.py
minotor/decorators/prediction_monitoring.py
minotor/encoders/__init__.py
minotor/encoders/json_encoder.py
minotor/encoders/json_encoder_library.py
minotor/front/build/asset-manifest.json
minotor/front/build/index.html
minotor/front/build/manifest.json
minotor/front/build/precache-manifest.cc82c94b8a38a2e35481e23ee66d76b4.js
minotor/front/build/service-worker.js
minotor/front/build/static/css/2.5a2f7233.chunk.css
minotor/front/build/static/css/2.5a2f7233.chunk.css.map
minotor/front/build/static/css/main.adb9c03c.chunk.css
minotor/front/build/static/css/main.adb9c03c.chunk.css.map
minotor/front/build/static/js/2.4dd24e80.chunk.js
minotor/front/build/static/js/2.4dd24e80.chunk.js.LICENSE.txt
minotor/front/build/static/js/2.4dd24e80.chunk.js.map
minotor/front/build/static/js/main.bc16927b.chunk.js
minotor/front/build/static/js/main.bc16927b.chunk.js.map
minotor/front/build/static/js/runtime-main.460b34f2.js
minotor/front/build/static/js/runtime-main.460b34f2.js.map
minotor/front/build/static/media/Poppins-Black.42cf9f08.ttf
minotor/front/build/static/media/Poppins-Bold.c23534ac.ttf
minotor/front/build/static/media/Poppins-Italic.89c81a3c.ttf
minotor-0.0.2.dist-info/LICENSE.txt
minotor-0.0.2.dist-info/METADATA
minotor-0.0.2.dist-info/WHEEL
minotor-0.0.2.dist-info/entry_points.txt
minotor-0.0.2.dist-info/top_level.txt
minotor-0.0.2.dist-info/RECORD
